[{
  "_id": {
    "$oid": "64b646829efe6eb43f931918"
  },
  "title": "Always",
  "track_count": "11609691",
  "periodOfTime": "2023"
},
{
  "_id": {
    "$oid": "64b646829efe6eb43f931919"
  },
  "title": "Easy",
  "track_count": "5386517",
  "periodOfTime": "2017"
},
{
  "_id": {
    "$oid": "64b646829efe6eb43f93191a"
  },
  "title": "Movie",
  "track_count": "4301366",
  "periodOfTime": "2018"
},
{
  "_id": {
    "$oid": "64b646829efe6eb43f93191b"
  },
  "title": "Call You Mine",
  "track_count": "4289298",
  "periodOfTime": "2011"
},
{
  "_id": {
    "$oid": "64b646829efe6eb43f93191c"
  },
  "title": "Janji Setia",
  "track_count": "3598697",
  "periodOfTime": "2021"
},
{
  "_id": {
    "$oid": "64b646829efe6eb43f93191d"
  },
  "title": "Ragu",
  "track_count": "3368608",
  "periodOfTime": "2018"
},
{
  "_id": {
    "$oid": "64b646829efe6eb43f93191e"
  },
  "title": "Home",
  "track_count": "3341803",
  "periodOfTime": "2017"
},
{
  "_id": {
    "$oid": "64b646829efe6eb43f93191f"
  },
  "title": "No Other Heart",
  "track_count": "3251799",
  "periodOfTime": "2015"
},
{
  "_id": {
    "$oid": "64b646829efe6eb43f931920"
  },
  "title": "Could It Be",
  "track_count": "3225161",
  "periodOfTime": "2011"
},
{
  "_id": {
    "$oid": "64b646829efe6eb43f931921"
  },
  "title": "Sulung",
  "track_count": "31644693",
  "periodOfTime": "2018"
}]